compal_wifi_switch/__init__.py
compal_wifi_switch/main.py
compal_wifi_switch-1.2.2.dist-info/LICENSE.txt
compal_wifi_switch-1.2.2.dist-info/METADATA
compal_wifi_switch-1.2.2.dist-info/WHEEL
compal_wifi_switch-1.2.2.dist-info/entry_points.txt
compal_wifi_switch-1.2.2.dist-info/top_level.txt
compal_wifi_switch-1.2.2.dist-info/zip-safe
compal_wifi_switch-1.2.2.dist-info/RECORD
