Metadata-Version: 2.1
Name: compal-wifi-switch
Version: 1.2.2
Summary: CLI tool to switch on/off the wifi module of a Compal cabelmodem (CH7465LG/Ziggo Connect Box)
Home-page: https://github.com/frimtec/compal-wifi-switch
Author: Markus Friedli
Author-email: frimtec@gmx.ch
License: Apache 2
Keywords: compal CH7465LG connect box cablemodem wifi switch
Platform: UNKNOWN
Classifier: Programming Language :: Python :: 3
Classifier: License :: OSI Approved :: Apache Software License
Classifier: Operating System :: OS Independent
Requires-Python: >=3.7
License-File: LICENSE.txt
Requires-Dist: compal
